{
  "parameters": [
    {
      "type": "ParameterTypeNumber",
      "index": 0,
      "name": "drywet",
      "paramId": "drywet",
      "minimum": 0,
      "maximum": 1,
      "exponent": 1,
      "steps": 0,
      "initialValue": 0,
      "isEnum": false,
      "enumValues": [],
      "displayName": "",
      "unit": "",
      "order": 0,
      "debug": false,
      "visible": true,
      "signalIndex": null,
      "ioType": "IOTypeUndefined"
    },
    {
      "type": "ParameterTypeNumber",
      "index": 1,
      "name": "freeze",
      "paramId": "record/freeze",
      "minimum": 0,
      "maximum": 1,
      "exponent": 1,
      "steps": 2,
      "initialValue": 0,
      "isEnum": true,
      "enumValues": [
        "off",
        "on"
      ],
      "displayName": "",
      "unit": "",
      "order": 0,
      "debug": false,
      "visible": true,
      "signalIndex": null,
      "ioType": "IOTypeUndefined"
    },
    {
      "type": "ParameterTypeNumber",
      "index": 2,
      "name": "frequency",
      "paramId": "feedback/frequency",
      "minimum": 0,
      "maximum": 22050,
      "exponent": 1,
      "steps": 0,
      "initialValue": 800,
      "isEnum": false,
      "enumValues": [],
      "displayName": "",
      "unit": "Hz",
      "order": 0,
      "debug": false,
      "visible": true,
      "signalIndex": null,
      "ioType": "IOTypeUndefined"
    },
    {
      "type": "ParameterTypeNumber",
      "index": 3,
      "name": "resonance",
      "paramId": "feedback/resonance",
      "minimum": 0,
      "maximum": 1,
      "exponent": 1,
      "steps": 0,
      "initialValue": 0,
      "isEnum": false,
      "enumValues": [],
      "displayName": "",
      "unit": "",
      "order": 0,
      "debug": false,
      "visible": true,
      "signalIndex": null,
      "ioType": "IOTypeUndefined"
    },
    {
      "type": "ParameterTypeNumber",
      "index": 4,
      "name": "amount",
      "paramId": "feedback/amount",
      "minimum": -70,
      "maximum": 30,
      "exponent": 1,
      "steps": 0,
      "initialValue": -70,
      "isEnum": false,
      "enumValues": [],
      "displayName": "",
      "unit": "dB",
      "order": 0,
      "debug": false,
      "visible": true,
      "signalIndex": null,
      "ioType": "IOTypeUndefined"
    },
    {
      "type": "ParameterTypeNumber",
      "index": 5,
      "name": "type",
      "paramId": "feedback/type",
      "minimum": 0,
      "maximum": 3,
      "exponent": 1,
      "steps": 4,
      "initialValue": 0,
      "isEnum": true,
      "enumValues": [
        "bypass",
        "lowpass",
        "hightpass",
        "bandpass"
      ],
      "displayName": "",
      "unit": "",
      "order": 0,
      "debug": false,
      "visible": true,
      "signalIndex": null,
      "ioType": "IOTypeUndefined"
    },
    {
      "type": "ParameterTypeNumber",
      "index": 6,
      "name": "density",
      "paramId": "trigger/density",
      "minimum": 0,
      "maximum": 2000,
      "exponent": 1,
      "steps": 0,
      "initialValue": 1,
      "isEnum": false,
      "enumValues": [],
      "displayName": "",
      "unit": "Hz",
      "order": 0,
      "debug": false,
      "visible": true,
      "signalIndex": null,
      "ioType": "IOTypeUndefined"
    },
    {
      "type": "ParameterTypeNumber",
      "index": 7,
      "name": "probability",
      "paramId": "trigger/probability",
      "minimum": 0,
      "maximum": 1,
      "exponent": 1,
      "steps": 0,
      "initialValue": 1,
      "isEnum": false,
      "enumValues": [],
      "displayName": "",
      "unit": "",
      "order": 0,
      "debug": false,
      "visible": true,
      "signalIndex": null,
      "ioType": "IOTypeUndefined"
    },
    {
      "type": "ParameterTypeNumber",
      "index": 8,
      "name": "position_spread_min",
      "paramId": "cloud/position_spread_min",
      "minimum": 0,
      "maximum": 10000,
      "exponent": 1,
      "steps": 0,
      "initialValue": 0,
      "isEnum": false,
      "enumValues": [],
      "displayName": "",
      "unit": "ms",
      "order": 0,
      "debug": false,
      "visible": true,
      "signalIndex": null,
      "ioType": "IOTypeUndefined"
    },
    {
      "type": "ParameterTypeNumber",
      "index": 9,
      "name": "position_spread_max",
      "paramId": "cloud/position_spread_max",
      "minimum": 0,
      "maximum": 10000,
      "exponent": 1,
      "steps": 0,
      "initialValue": 100,
      "isEnum": false,
      "enumValues": [],
      "displayName": "",
      "unit": "ms",
      "order": 0,
      "debug": false,
      "visible": true,
      "signalIndex": null,
      "ioType": "IOTypeUndefined"
    },
    {
      "type": "ParameterTypeNumber",
      "index": 10,
      "name": "size_min",
      "paramId": "cloud/size_min",
      "minimum": 0.00001,
      "maximum": 10000,
      "exponent": 1,
      "steps": 0,
      "initialValue": 50,
      "isEnum": false,
      "enumValues": [],
      "displayName": "",
      "unit": "ms",
      "order": 0,
      "debug": false,
      "visible": true,
      "signalIndex": null,
      "ioType": "IOTypeUndefined"
    },
    {
      "type": "ParameterTypeNumber",
      "index": 11,
      "name": "size_max",
      "paramId": "cloud/size_max",
      "minimum": 0.00001,
      "maximum": 10000,
      "exponent": 1,
      "steps": 0,
      "initialValue": 50,
      "isEnum": false,
      "enumValues": [],
      "displayName": "",
      "unit": "ms",
      "order": 0,
      "debug": false,
      "visible": true,
      "signalIndex": null,
      "ioType": "IOTypeUndefined"
    },
    {
      "type": "ParameterTypeNumber",
      "index": 12,
      "name": "window_saw_min",
      "paramId": "cloud/window_saw_min",
      "minimum": 0,
      "maximum": 1,
      "exponent": 1,
      "steps": 0,
      "initialValue": 0.5,
      "isEnum": false,
      "enumValues": [],
      "displayName": "",
      "unit": "",
      "order": 0,
      "debug": false,
      "visible": true,
      "signalIndex": null,
      "ioType": "IOTypeUndefined"
    },
    {
      "type": "ParameterTypeNumber",
      "index": 13,
      "name": "window_saw_max",
      "paramId": "cloud/window_saw_max",
      "minimum": 0,
      "maximum": 1,
      "exponent": 1,
      "steps": 0,
      "initialValue": 0.5,
      "isEnum": false,
      "enumValues": [],
      "displayName": "",
      "unit": "",
      "order": 0,
      "debug": false,
      "visible": true,
      "signalIndex": null,
      "ioType": "IOTypeUndefined"
    },
    {
      "type": "ParameterTypeNumber",
      "index": 14,
      "name": "window_square_min",
      "paramId": "cloud/window_square_min",
      "minimum": 0,
      "maximum": 1,
      "exponent": 1,
      "steps": 0,
      "initialValue": 0,
      "isEnum": false,
      "enumValues": [],
      "displayName": "",
      "unit": "",
      "order": 0,
      "debug": false,
      "visible": true,
      "signalIndex": null,
      "ioType": "IOTypeUndefined"
    },
    {
      "type": "ParameterTypeNumber",
      "index": 15,
      "name": "window_square_max",
      "paramId": "cloud/window_square_max",
      "minimum": 0,
      "maximum": 1,
      "exponent": 1,
      "steps": 0,
      "initialValue": 0,
      "isEnum": false,
      "enumValues": [],
      "displayName": "",
      "unit": "",
      "order": 0,
      "debug": false,
      "visible": true,
      "signalIndex": null,
      "ioType": "IOTypeUndefined"
    },
    {
      "type": "ParameterTypeNumber",
      "index": 16,
      "name": "reverse_prob",
      "paramId": "cloud/reverse_prob",
      "minimum": 0,
      "maximum": 1,
      "exponent": 1,
      "steps": 0,
      "initialValue": 0,
      "isEnum": false,
      "enumValues": [],
      "displayName": "",
      "unit": "",
      "order": 0,
      "debug": false,
      "visible": true,
      "signalIndex": null,
      "ioType": "IOTypeUndefined"
    },
    {
      "type": "ParameterTypeNumber",
      "index": 17,
      "name": "stereo_spread",
      "paramId": "cloud/stereo_spread",
      "minimum": 0,
      "maximum": 1,
      "exponent": 1,
      "steps": 0,
      "initialValue": 0,
      "isEnum": false,
      "enumValues": [],
      "displayName": "",
      "unit": "",
      "order": 0,
      "debug": false,
      "visible": true,
      "signalIndex": null,
      "ioType": "IOTypeUndefined"
    },
    {
      "type": "ParameterTypeNumber",
      "index": 18,
      "name": "amp_spread",
      "paramId": "cloud/amp_spread",
      "minimum": 0,
      "maximum": 1,
      "exponent": 1,
      "steps": 0,
      "initialValue": 0,
      "isEnum": false,
      "enumValues": [],
      "displayName": "",
      "unit": "",
      "order": 0,
      "debug": false,
      "visible": true,
      "signalIndex": null,
      "ioType": "IOTypeUndefined"
    },
    {
      "type": "ParameterTypeNumber",
      "index": 19,
      "name": "arp",
      "paramId": "cloud/arp",
      "minimum": 0,
      "maximum": 1,
      "exponent": 1,
      "steps": 2,
      "initialValue": 0,
      "isEnum": true,
      "enumValues": [
        "off",
        "on"
      ],
      "displayName": "",
      "unit": "",
      "order": 0,
      "debug": false,
      "visible": true,
      "signalIndex": null,
      "ioType": "IOTypeUndefined"
    },
    {
      "type": "ParameterTypeNumber",
      "index": 20,
      "name": "pitch_spread",
      "paramId": "cloud/pitch_spread",
      "minimum": 0,
      "maximum": 1200,
      "exponent": 1,
      "steps": 0,
      "initialValue": 0,
      "isEnum": false,
      "enumValues": [],
      "displayName": "",
      "unit": "",
      "order": 0,
      "debug": false,
      "visible": true,
      "signalIndex": null,
      "ioType": "IOTypeUndefined"
    }
  ],
  "numParameters": 21,
  "numSignalInParameters": 0,
  "numSignalOutParameters": 0,
  "numInputChannels": 2,
  "numOutputChannels": 2,
  "numMidiInputPorts": 1,
  "numMidiOutputPorts": 0,
  "externalDataRefs": [],
  "patcherSerial": 0,
  "inports": [],
  "outports": [],
  "inlets": [
    {
      "type": "signal",
      "index": 1,
      "tag": "in1",
      "meta": "",
      "comment": "input L"
    },
    {
      "type": "signal",
      "index": 2,
      "tag": "in2",
      "meta": "",
      "comment": "input R"
    },
    {
      "type": "midi"
    }
  ],
  "outlets": [
    {
      "type": "signal",
      "index": 1,
      "tag": "out1",
      "meta": "",
      "comment": "output L"
    },
    {
      "type": "signal",
      "index": 2,
      "tag": "out2",
      "meta": "",
      "comment": "output R"
    }
  ],
  "presetid": "rnbo",
  "meta": {
    "architecture": "x64",
    "filename": "lulu.maxpat",
    "rnboobjname": "rnbomatic",
    "maxversion": "8.6.2",
    "rnboversion": "1.2.6",
    "name": "lulu"
  }
}